backpack_tf/__init__.py
backpack_tf/backpack_tf.py
backpack_tf/classes.py
backpack_tf/exceptions.py
backpack_tf/utils.py
backpack_tf/websocket.py
bptf-0.1.4.dist-info/licenses/LICENSE
bptf-0.1.4.dist-info/METADATA
bptf-0.1.4.dist-info/WHEEL
bptf-0.1.4.dist-info/top_level.txt
bptf-0.1.4.dist-info/RECORD
