Metadata-Version: 2.4
Name: bptf
Version: 0.1.4
Summary: Create and manage Backpack.tf listings (API v2) using Python 3
Author-email: offish <overutilization@gmail.com>
Project-URL: Homepage, https://github.com/offish/backpack-tf
Project-URL: Bug Tracker, https://github.com/offish/backpack-tf/issues
Keywords: tf2,backpack-tf,utils,sku
Classifier: Programming Language :: Python :: 3
Classifier: License :: OSI Approved :: MIT License
Classifier: Operating System :: OS Independent
Requires-Python: >=3.10
License-File: LICENSE
Requires-Dist: tf2-utils
Requires-Dist: requests
Requires-Dist: websockets
Dynamic: license-file
